gh_md_to_html/__init__.py
gh_md_to_html/__main__.py
gh_md_to_html/code-navigation-banner-illo.svg
gh_md_to_html/core_converter.py
gh_md_to_html/github-css.css
gh_md_to_html/github-css.min.css
gh_md_to_html/help.txt
gh_md_to_html/helpers.py
gh_md_to_html/latex2svg.py
gh_md_to_html/prototype.html
gh_md_to_html/windows_shellescape.py
gh_md_to_html-1.21.3.data/scripts/gh-md-to-html
gh_md_to_html-1.21.3.dist-info/LICENSE.txt
gh_md_to_html-1.21.3.dist-info/METADATA
gh_md_to_html-1.21.3.dist-info/WHEEL
gh_md_to_html-1.21.3.dist-info/top_level.txt
gh_md_to_html-1.21.3.dist-info/RECORD
