Metadata-Version: 2.1
Name: gh-md-to-html
Version: 1.21.3
Summary: Feature-rich Github-flavored Markdown to html python and command line interface.
Home-page: https://github.com/phseiff/github-flavored-markdown-to-html/
Author: phseiff
Author-email: phseiff@phseiff.com
License: LICENSE.txt
Platform: UNKNOWN
Classifier: Programming Language :: Python :: 3
Requires-Python: >=3.6
Provides-Extra: offline_conversion
Provides-Extra: pdf_export
